vinclient_petstore_ti/__init__.py
vinclient_petstore_ti/api_client.py
vinclient_petstore_ti/api_response.py
vinclient_petstore_ti/configuration.py
vinclient_petstore_ti/exceptions.py
vinclient_petstore_ti/py.typed
vinclient_petstore_ti/rest.py
vinclient_petstore_ti/api/__init__.py
vinclient_petstore_ti/api/pet_api.py
vinclient_petstore_ti/api/store_api.py
vinclient_petstore_ti/api/user_api.py
vinclient_petstore_ti/models/__init__.py
vinclient_petstore_ti/models/address.py
vinclient_petstore_ti/models/api_response.py
vinclient_petstore_ti/models/category.py
vinclient_petstore_ti/models/customer.py
vinclient_petstore_ti/models/order.py
vinclient_petstore_ti/models/pet.py
vinclient_petstore_ti/models/tag.py
vinclient_petstore_ti/models/user.py
vinclient_petstore_ti-0.0.1.dist-info/METADATA
vinclient_petstore_ti-0.0.1.dist-info/WHEEL
vinclient_petstore_ti-0.0.1.dist-info/top_level.txt
vinclient_petstore_ti-0.0.1.dist-info/RECORD
